effCTR/__init__.py
effCTR-0.1.0.dist-info/METADATA
effCTR-0.1.0.dist-info/WHEEL
effCTR-0.1.0.dist-info/top_level.txt
effCTR-0.1.0.dist-info/RECORD
