Metadata-Version: 2.1
Name: effCTR
Version: 0.1.0
Summary: UNKNOWN
Home-page: https://github.com/ksolarski/effCTR
Author: Kacper Solarski
Author-email: pchla10@gmail.com
License: UNKNOWN
Platform: UNKNOWN
Requires-Dist: matplotlib (==3.5.2)
Requires-Dist: numpy (==1.23.0)
Requires-Dist: scipy (==1.8.1)
Requires-Dist: pyparsing (==3.0.9) ; python_full_version >= "3.6.8"
Requires-Dist: python-dateutil (==2.8.2) ; python_version >= "2.7" and python_version not in "3.0, 3.1, 3.2, 3.3"
Requires-Dist: six (==1.16.0) ; python_version >= "2.7" and python_version not in "3.0, 3.1, 3.2, 3.3"
Requires-Dist: cycler (==0.11.0) ; python_version >= "3.6"
Requires-Dist: packaging (==21.3) ; python_version >= "3.6"
Requires-Dist: fonttools (==4.33.3) ; python_version >= "3.7"
Requires-Dist: kiwisolver (==1.4.3) ; python_version >= "3.7"
Requires-Dist: pillow (==9.1.1) ; python_version >= "3.7"
